invenio_orcid/__init__.py
invenio_orcid/config.py
invenio_orcid/ext.py
invenio_orcid/models.py
invenio_orcid/proxies.py
invenio_orcid/receivers.py
invenio_orcid/tasks.py
invenio_orcid/utils.py
invenio_orcid/version.py
invenio_orcid/views.py
invenio_orcid/serializers/__init__.py
invenio_orcid/serializers/orcid_serializer.py
invenio_orcid/templates/invenio_orcid/base.html
invenio_orcid/templates/invenio_orcid/index.html
invenio_orcid-1.0.0a1.dist-info/DESCRIPTION.rst
invenio_orcid-1.0.0a1.dist-info/entry_points.txt
invenio_orcid-1.0.0a1.dist-info/METADATA
invenio_orcid-1.0.0a1.dist-info/metadata.json
invenio_orcid-1.0.0a1.dist-info/RECORD
invenio_orcid-1.0.0a1.dist-info/top_level.txt
invenio_orcid-1.0.0a1.dist-info/WHEEL
